{
    "format_version": "1.20.0",
    "minecraft:item": {
        "description" :{
            "identifier": "hog:exploding",
            "category": "Items"
        },
        "components": {
            "minecraft:icon": {
                "texture": "book_enchanted"
            },
            "minecraft:foil": true,
            "minecraft:display_name": {
                "value": "§eEnchanted Book\n§7Exploding\n§eInfo: §7Has a chance to explode when taking\ndamage.\n§eEquipment: §7Chestplate"
            }
        }
    }
}